jianzheng/__init__.py
jianzheng/base/__init__.py
jianzheng/base/exceptions.py
jianzheng-1.1.0.dist-info/LICENSE
jianzheng-1.1.0.dist-info/METADATA
jianzheng-1.1.0.dist-info/WHEEL
jianzheng-1.1.0.dist-info/top_level.txt
jianzheng-1.1.0.dist-info/RECORD
