Metadata-Version: 2.1
Name: jianzheng
Version: 1.1.0
Summary: Some fast-to-use APIs those provide ML solutions.
Home-page: https://github.com/JianzhengLuo/jianzheng
Author: Jianzheng Luo
Author-email: jianzheng.luo.china@gmail.com
License: Apache 2.0
Project-URL: Bug Tracker, https://github.com/JianzhengLuo/jianzheng/issues
Platform: UNKNOWN
Classifier: Development Status :: 1 - Planning
Classifier: Intended Audience :: Developers
Classifier: Intended Audience :: Education
Classifier: Intended Audience :: Science/Research
Classifier: License :: OSI Approved :: Apache Software License
Classifier: Natural Language :: English
Classifier: Programming Language :: Python :: 3.8
Requires-Python: >=3.8
License-File: LICENSE
